ephemerun/__init__.py
ephemerun/__main__.py
ephemerun/main.py
ephemerun-1.1.1.dist-info/METADATA
ephemerun-1.1.1.dist-info/WHEEL
ephemerun-1.1.1.dist-info/entry_points.txt
ephemerun-1.1.1.dist-info/top_level.txt
ephemerun-1.1.1.dist-info/RECORD
