Metadata-Version: 2.1
Name: ephemerun
Version: 1.1.1
Summary: Run actions in disposable containers
Home-page: https://github.com/pscl4rke/ephemerun
Author: P. S. Clarke
Author-email: ephemerun@pscl4rke.net
License: cf:licence
Project-URL: Source Code, https://github.com/pscl4rke/ephemerun
Project-URL: Issues, https://github.com/pscl4rke/ephemerun/issues
Project-URL: Licence, https://github.com/pscl4rke/ephemerun/blob/master/LICENCE.txt
Classifier: Development Status :: 5 - Production/Stable
Classifier: Intended Audience :: Developers
Classifier: Intended Audience :: Information Technology
Classifier: Programming Language :: Python :: 3.8
Classifier: Programming Language :: Python :: 3.9
Classifier: Programming Language :: Python :: 3.10
Classifier: Programming Language :: Python :: 3.11
Classifier: Programming Language :: Python :: 3.12
Classifier: Programming Language :: Python :: 3.13
Classifier: Topic :: Software Development :: Build Tools
Classifier: Topic :: Software Development :: Testing
Classifier: Topic :: Utilities
Requires-Python: >=3.8
Provides-Extra: testing
Requires-Dist: mypy ; extra == 'testing'
Requires-Dist: pyroma ; extra == 'testing'
